CHANGES.rst
DESCRIPTION.rst
LICENSE
MANIFEST.in
README.md
setup.py
src/wai.annotations.festvox.egg-info/PKG-INFO
src/wai.annotations.festvox.egg-info/SOURCES.txt
src/wai.annotations.festvox.egg-info/dependency_links.txt
src/wai.annotations.festvox.egg-info/entry_points.txt
src/wai.annotations.festvox.egg-info/namespace_packages.txt
src/wai.annotations.festvox.egg-info/requires.txt
src/wai.annotations.festvox.egg-info/top_level.txt
src/wai/annotations/festvox/__init__.py
src/wai/annotations/festvox/component/_FestVoxReader.py
src/wai/annotations/festvox/component/_FestVoxWriter.py
src/wai/annotations/festvox/component/__init__.py
src/wai/annotations/festvox/specifier/_FestVoxInputFormatSpecifier.py
src/wai/annotations/festvox/specifier/_FestVoxOutputFormatSpecifier.py
src/wai/annotations/festvox/specifier/__init__.py
src/wai/annotations/festvox/util/__init__.py
src/wai/annotations/festvox/util/_regex.py